{
  "version": "6.4.3",
  "description": "Code intelligence tool that builds semantic knowledge graphs from source code",
  "homepage": "https://github.com/aovestdipaperino/tokensave",
  "license": "MIT",
  "architecture": {
    "64bit": {
      "url": "https://github.com/aovestdipaperino/tokensave/releases/download/v6.4.3/tokensave-v6.4.3-x86_64-windows.zip",
      "hash": "0e56dde4ac097ef6b2bb5a1edaddd4d5f1f97620c0a94c9550789b67dd663302"
    }
  },
  "bin": "tokensave.exe",
  "checkver": {
    "github": "https://github.com/aovestdipaperino/tokensave"
  },
  "autoupdate": {
    "architecture": {
      "64bit": {
        "url": "https://github.com/aovestdipaperino/tokensave/releases/download/v$version/tokensave-v$version-x86_64-windows.zip"
      }
    }
  }
}
